webapp/__init__.py
webapp/antimonyTools.py
webapp/forms.py
webapp/routes.py
AMC_OWMV-1.0.1.dist-info/LICENSE
AMC_OWMV-1.0.1.dist-info/METADATA
AMC_OWMV-1.0.1.dist-info/WHEEL
AMC_OWMV-1.0.1.dist-info/top_level.txt
AMC_OWMV-1.0.1.dist-info/RECORD
