Metadata-Version: 2.1
Name: AMC-OWMV
Version: 1.0.1
Summary: Produce Antimony Files and Graphs using a browser GUI
Author-email: Olivia Walsh <owalsh@uw.edu>, Matthew Van Ginneken <mattcvang@gmail.com>
License: MIT License
Project-URL: Homepage, https://github.com/MatthewVanG/AMC-OWMVG
Requires-Python: >=3.9
License-File: LICENSE
Requires-Dist: tellurium
Requires-Dist: flask
Requires-Dist: wtforms
Requires-Dist: matplotlib
